<?xml version="1.0" encoding="UTF-8"?>
<NominaElectronica>
  <Conceptos>
	<Tercero>10112541451</Tercero>
	<!-- Numero identificación empleado -->
    <Documento>NE</Documento>
    <!-- Indicar el tipo de nómina que corresponde:
		 NE: NORMAL
		 NN: NOVEDAD
		 NA: AJUSTE REEMPLAZAR
		 NX: AJUSTE ELIMINAR-->
    <Documento1></Documento1>
    <!-- Si corresponde a una nota de ajuste o a una nómina de novedad referenciar el documento que lo precede
         NE: Nomina Normal Origen-->
    <Numero1>0</Numero1>
    <!-- Si corresponde a una nota de ajuste o a una nómina de novedad referenciar el Numero de NE  que lo precede-->
    <Concepto>ING</Concepto>
    <!-- Conceptos Liquidados por Empleado. Remitirse al archivo de diccionario de datos en la pestaña de Conceptos donde está el codigo a registrar.
		 NOTA: Cuando sea un empleado nuevo, se debe incluir el concepto ING, para realizar ingreso automatico.  
		 En caso de existir un retiro deben incluir un registro con el concepto RET.  -->
    <Entidad>0</Entidad>
    <!-- NIT de la entidad (Entidad Financiera) para el caso de libranzas, este tercero debe estar previamente creado [BTER], Default 0 en caso de no aplicar -->
    <Cantidad>0</Cantidad>
    <!-- Cantidad en dias por cada concepto, Default 0 en caso de no aplicar -->
    <Valor>0</Valor>
    <!-- Valor por cada concepto liquidado. Default 0 en caso de no aplicar -->
    <Tarifa>0</Tarifa>
    <!-- Tarifa (%) practicada en la liquidacion de cada concepto. Default 0 en caso de no aplicar -->
    <FechaInicial>1/05/2021</FechaInicial>
    <!-- Fecha Inicial concepto liquidado, en caso de no aplicar enviar vacio.
		 NOTA: Para los registros de ING o RET incluir fecha ingreso o retiro correspondiente -->
    <FechaFinal></FechaFinal>
    <!-- Fecha Final concepto liquidado, en caso de no aplicar enviar vacio.
		 NOTA: Para los registros de ING, incluir final contrato, si tiene unperiodo fijo cde contratación -->
    <Numero>130</Numero>
    <!-- Numero desprendible de la nomina sin prefijo -->
    <FechaInicialPago>1/05/2021</FechaInicialPago>
    <!-- Fecha Inicial del periodo liquidado para el pago -->
    <FechaFinalPago>31/05/2021</FechaFinalPago>
    <!-- Fecha Final del periodo liquidado para el pago -->
	<TipoTercero>C</TipoTercero>
	<!-- Tipo Documento Empleado:
		C: CEDULA
		N: NIT
		X: EXTRANJERIA
		P: PASAPORTE
		I: TARJETA IDENTIDAD
		O: OTRO
		R: REGISTRO CIVIL
		E: PERMISO ESPECIAL
		J: NIT EXTRANJERO -->
    <PrimerApellido>PEREZ</PrimerApellido>
    <!-- Primer Apellido Empleado -->
    <SegundoApellido></SegundoApellido>
    <!-- Segundo Apellido Empleado, si no aplica enviar un espacio -->
    <PrimerNombre>pedroprueba</PrimerNombre>
    <!-- Primer Nombre  Empleado -->
    <SegundoNombre></SegundoNombre>
    <!-- Segundo Nombre Empleado, si no aplica enviar un espacio -->
    <UbicacionLaboral>1</UbicacionLaboral>
    <!-- Código Ubicacion Laboral empleado en caso de tener diferentes ubicaciones laborales 
    	 1: Ubicación Principal-->
    <CorreoElectronico>pedroprueba.perez@gmail.com</CorreoElectronico>
    <!-- Correo electronico empleado -->
    <Celular>3502369874</Celular>
    <!-- Numero celular empleado -->
	<Banco>51</Banco>
	<!-- Código Compensación Banco (según BRC) de la cuenta Bancaria Empleado -->
	<TipoCuenta>A</TipoCuenta>
	<!-- Tipo Cuenta Empleado: -->
	<!-- A: AHORROS -->
	<!-- C: CORRIENTE -->
	<!-- D: DAVIPLATA -->
	<!-- S: AHORRO COLECTIVO -->
	<!-- N: NEQUI -->
	<!-- E: EFECTIVO -->
	<!-- O: OTRO -->
	<CuentaBancaria>1325997846</CuentaBancaria>
	<!-- Numero cuenta bancaria empleado, en caso de Daviplata, Nequi número de celular -->
	<TipoNomina>4</TipoNomina>
	<!-- Tipo Nomina Empleado: -->
    <!-- 1: SEMANAL -->
    <!-- 2: DECENAL -->
    <!-- 3: CATORCENAL -->
    <!-- 4: QUINCENAL -->
    <!-- 5: MENSUAL -->
    <!-- 6: OTRO -->
	<TipoContrato>0</TipoContrato>
	<!-- Tipo Contrato Empleado: -->
	<!-- 0: TERMINO INDEFINIDO -->
	<!-- 1: TERMINO FIJO -->
	<!-- 2: OBRA LABOR -->
	<!-- 3: APRENDIZAJE -->
	<!-- 4: PRACTICAS O PASANTIAS -->
	<TipoSalario>N</TipoSalario>
	<!-- Tipo Salario Empleado: -->
	<!-- N: NORMAL -->
	<!-- V: VARIABLE -->
	<!-- I: INTEGRAL -->
	<Salario>1200000</Salario>
	<!-- Salario basico con el cual fue contratado el empleado -->
	<Cargo>0</Cargo>
	<!-- Codigo del cargo (Definir lista de cargos y enviarla en el proceso de Imlementación)
		 0: Indefinido -->
	<EmpleadoAltoRiesgo>0</EmpleadoAltoRiesgo>
	<!-- Indicar si el empleado es alto riesgo
		 0: No es Alto Riesgo
		 1: Es Alto Riesgo -->
	<TipoEmpleado>0</TipoEmpleado>
	<!-- Código del Tipo de Empleado: -->
	<!-- 0: NORMAL -->
	<!-- 1: MEDIO TIEMPO -->
	<!-- 2: ALTO RIESGO -->
	<!-- 3: EN PROCESO DE PENSIÓN -->
	<!-- 4: PENSIONADO ALTO RIESGO -->
	<!-- 10: PENSIONADO -->
	<!-- 11: SALARIO INTEGRAL -->
	<!-- 12: APRENDIZ ETAPA LECTIVA -->
	<!-- 19: APRENDIZ ETAPA PRODUCTIVA -->
	<!-- 23: PASANTE UNIVERSITARIO -->
	<Notas></Notas>
	<!-- Observaciones sobre la nomina -->
	<MetodoPago>ZZZ</MetodoPago>
	<!-- Codigo del metodo de pago de nomina según Tabla 5.3.3.2 Res. 000013 -->
	<!-- ZZZ: Acuerdo Mutuo -->
  </Conceptos>
  <Conceptos>
    <Tercero>10112541451</Tercero>
    <Documento>NE</Documento>
    <Documento1></Documento1>
    <Numero1>0</Numero1>
    <Concepto>SUE</Concepto>
	<Entidad>0</Entidad>
    <Cantidad>30</Cantidad>
    <Valor>2907100</Valor>
    <Tarifa>0</Tarifa>
    <FechaInicial>1/05/2021</FechaInicial>
    <FechaFinal></FechaFinal>
    <Numero>130</Numero>
    <FechaInicialPago>1/05/2021</FechaInicialPago>
    <FechaFinalPago>31/05/2021</FechaFinalPago>
	<TipoTercero>C</TipoTercero>
    <PrimerApellido>PEREZ</PrimerApellido>
    <SegundoApellido></SegundoApellido>
    <PrimerNombre>pedroprueba</PrimerNombre>
    <SegundoNombre></SegundoNombre>
    <UbicacionLaboral>1</UbicacionLaboral>
    <CorreoElectronico>pedroprueba.perez@gmail.com</CorreoElectronico>
    <Celular>3502369874</Celular>
	<Banco>51</Banco>
	<TipoCuenta>A</TipoCuenta>
	<CuentaBancaria>1325997846</CuentaBancaria>
	<TipoNomina>1</TipoNomina>
	<TipoContrato>0</TipoContrato>
	<TipoSalario>N</TipoSalario>
	<Salario>1200000</Salario>
	<Cargo></Cargo>-->
	<EmpleadoAltoRiesgo>0</EmpleadoAltoRiesgo>
	<TipoEmpleado></TipoEmpleado>
	<Notas></Notas>
	<MetodoPago></MetodoPago>
  </Conceptos>
  <Conceptos>
    <Tercero>10112541451</Tercero>
    <Documento>NE</Documento>
    <Documento1></Documento1>
    <Numero1>0</Numero1>
    <Concepto>SLN</Concepto>
    <Entidad>0</Entidad>
	<Cantidad>1</Cantidad>
    <Valor>1245900</Valor>
    <Tarifa>0</Tarifa>
    <FechaInicial>1/05/2021</FechaInicial>
    <FechaFinal></FechaFinal>
    <Numero>130</Numero>
    <FechaInicialPago>1/05/2021</FechaInicialPago>
    <FechaFinalPago>31/05/2021</FechaFinalPago>
	<TipoTercero>C</TipoTercero>
    <PrimerApellido>PEREZ</PrimerApellido>
    <SegundoApellido></SegundoApellido>
    <PrimerNombre>pedroprueba</PrimerNombre>
    <SegundoNombre></SegundoNombre>
    <UbicacionLaboral>1</UbicacionLaboral>
    <CorreoElectronico>pedroprueba.perez@gmail.com</CorreoElectronico>
    <Celular>3502369874</Celular>
	<Banco>51</Banco>
	<TipoCuenta>A</TipoCuenta>
	<CuentaBancaria>1325997846</CuentaBancaria>
	<TipoNomina>1</TipoNomina>
	<TipoContrato>0</TipoContrato>
	<TipoSalario>N</TipoSalario>
	<Salario>1200000</Salario>
	<Cargo></Cargo>
	<EmpleadoAltoRiesgo>0</EmpleadoAltoRiesgo>
	<TipoEmpleado></TipoEmpleado>
	<Notas></Notas>
	<MetodoPago></MetodoPago>
  </Conceptos>
</NominaElectronica>